definitions.py
bdgs/__init__.py
bdgs/classifier.py
bdgs/algorithms/__init__.py
bdgs/algorithms/bdgs_algorithm.py
bdgs/algorithms/adithya_rajesh/__init__.py
bdgs/algorithms/adithya_rajesh/adithya_rajesh.py
bdgs/algorithms/adithya_rajesh/adithya_rajesh_learning_data.py
bdgs/algorithms/adithya_rajesh/adithya_rajesh_payload.py
bdgs/algorithms/chang_chen/__init__.py
bdgs/algorithms/chang_chen/chang_chen.py
bdgs/algorithms/chang_chen/chang_chen_learning_data.py
bdgs/algorithms/chang_chen/chang_chen_payload.py
bdgs/algorithms/eid_schwenker/__init__.py
bdgs/algorithms/eid_schwenker/eid_schwenker.py
bdgs/algorithms/gupta_jaafar/__init__.py
bdgs/algorithms/gupta_jaafar/gupta_jaafar.py
bdgs/algorithms/gupta_jaafar/gupta_jaafar_learning_data.py
bdgs/algorithms/gupta_jaafar/gupta_jaafar_payload.py
bdgs/algorithms/islam_hossain_andersson/__init__.py
bdgs/algorithms/islam_hossain_andersson/islam_hossain_andersson.py
bdgs/algorithms/islam_hossain_andersson/islam_hossain_andersson_learning_data.py
bdgs/algorithms/islam_hossain_andersson/islam_hossain_andersson_payload.py
bdgs/algorithms/joshi_kumar/__init__.py
bdgs/algorithms/joshi_kumar/joshi_kumar.py
bdgs/algorithms/joshi_kumar/joshi_kumar_learning_data.py
bdgs/algorithms/joshi_kumar/joshi_kumar_payload.py
bdgs/algorithms/maung/__init__.py
bdgs/algorithms/maung/maung.py
bdgs/algorithms/maung/maung_learning_data.py
bdgs/algorithms/maung/maung_payload.py
bdgs/algorithms/mohanty_rambhatla/__init__.py
bdgs/algorithms/mohanty_rambhatla/mohanty_rambhatla.py
bdgs/algorithms/mohanty_rambhatla/mohanty_rambhatla_learning_data.py
bdgs/algorithms/mohanty_rambhatla/mohanty_rambhatla_payload.py
bdgs/algorithms/mohmmad_dadi/__init__.py
bdgs/algorithms/mohmmad_dadi/mohmmad_dadi.py
bdgs/algorithms/murthy_jadon/__init__.py
bdgs/algorithms/murthy_jadon/murthy_jadon.py
bdgs/algorithms/murthy_jadon/murthy_jadon_learning_data.py
bdgs/algorithms/murthy_jadon/murthy_jadon_payload.py
bdgs/algorithms/naidoo_omlin/__init__.py
bdgs-2.1.0.dist-info/licenses/LICENSE
bdgs-2.1.0.dist-info/METADATA
bdgs-2.1.0.dist-info/WHEEL
bdgs-2.1.0.dist-info/top_level.txt
bdgs-2.1.0.dist-info/RECORD
