Metadata-Version: 2.4
Name: bdgs
Version: 2.1.0
Summary: Static gestures recognition tool
Author: marcinbator
Author-email: marcinbator.ofc@gmail.com
Classifier: Programming Language :: Python :: 3
Classifier: License :: OSI Approved :: GNU Affero General Public License v3
Classifier: Operating System :: OS Independent
Requires-Python: >=3.11
License-File: LICENSE
Requires-Dist: opencv-python~=4.11.0.86
Requires-Dist: numpy~=2.1.3
Requires-Dist: tensorflow-cpu~=2.19.0
Requires-Dist: scikit-learn~=1.6.1
Requires-Dist: keras~=3.9.2
Requires-Dist: scikit-image~=0.25.2
Requires-Dist: silence-tensorflow~=1.2.3
Dynamic: author
Dynamic: author-email
Dynamic: classifier
Dynamic: description
Dynamic: description-content-type
Dynamic: license-file
Dynamic: requires-dist
Dynamic: requires-python
Dynamic: summary
